Workbook

Sheet Main
A1: Movie Name | B1: Scraped Name | C1: Budget | D1: Director | E1: Writer | F1: Actor | G1: Rating | H1: OtherInfo | I1: Date | J1: DirectorsRating | K1: WritersRating | L1: TotalFollowers | M1: Revenue
A2: Foodfight! | B2: Foodfight! | C2: 45000000 | D2: ['Lawrence Kasanoff'] | E2: ['Lawrence Kasanoff', 'Joshua Wexler', 'Brent V. Friedman'] | F2: ['Hilary Duff', 'Haylie Duff', 'Charlie Sheen'] | G2: 1.3 | H2: 2012 PG 1h 31m | I2: 2012 | J2: 1 | K2: 1.6666667 | L2: 18.30103 | M2: =_xlfn.XLOOKUP(A2,Revenue!A:A,Revenue!C:C) -> 120323
A3: Superbabies: Baby Geniuses 2 | B3: Superbabies: Baby Geniuses 2 | C3: 20000000 | D3: ['Bob Clark'] | E3: ['Robert Grasmere', 'Francisca Matos', 'Steven Paul'] | F3: ['Jon Voight', 'Scott Baio', 'Vanessa Angel'] | G3: 1.5 | H3: 2004 PG 1h 28m | I3: 2004 | J3: 7 | K3: 1.5 | L3: 7.6825602 | M3: =_xlfn.XLOOKUP(A3,Revenue!A:A,Revenue!C:C) -> 9355369
A4: The Oogieloves in the BIG Balloon Adventure | B4: The Oogieloves in the Big Balloon Adventure | C4: 20000000 | D4: ['Matthew Diamond'] | E4: ['Scott Stabile', 'Kenn Viselman', 'Alex J Greene'] | F4: ['Jaime Pressly', 'Cloris Leachman', 'Christopher Lloyd'] | G4: 1.7 | H4: 2012 G 1h 28m | I4: 2012 | J4: 1 | K4: 1 | L4: 11.450043 | M4: =_xlfn.XLOOKUP(A4,Revenue!A:A,Revenue!C:C) -> 1065907
A5: Justin Bieber: Never Say Never | B5: Justin Bieber: Never Say Never | C5: 13000000 | D5: ['Jon M. Chu'] | E5: ['Justin Bieber', 'Boyz II Men', 'Miley Cyrus'] | F5: ['Justin Bieber', 'Boyz II Men', 'Miley Cyrus'] | G5: 1.7 | H5: 2011 G 1h 45m | I5: 2011 | J5: 6.3333333 | K5: 1 | L5: 20.045591 | M5: =_xlfn.XLOOKUP(A5,Revenue!A:A,Revenue!C:C) -> 99034125
A6: Disaster Movie | B6: Disaster Movie | C6: 20000000 | D6: ['Jason Friedberg', 'Aaron Seltzer'] | E6: ['Jason Friedberg', 'Aaron Seltzer'] | F6: ['Carmen Electra', 'Vanessa Lachey', 'Nicole Parker'] | G6: 1.9 | H6: 2008 PG-13 1h 27m | I6: 2008 | J6: 2.3333333 | K6: 3.3333333 | L6: 18.60206 | M6: =_xlfn.XLOOKUP(A6,Revenue!A:A,Revenue!C:C) -> 36720752
A7: From Justin to Kelly | B7: From Justin to Kelly | C7: 12000000 | D7: ['Robert Iscove'] | E7: ['Kim Fuller'] | F7: ['Kelly Clarkson', 'Justin Guarini', 'Katherine Bailess'] | G7: 1.9 | H7: 2003 PG 1h 21m | I7: 2003 | J7: 3.6666667 | K7: 3.3333333 | L7: 15.090628 | M7: =_xlfn.XLOOKUP(A7,Revenue!A:A,Revenue!C:C) -> 4922166
A8: United Passions | B8: United Passions | C8: 30000000 | D8: ['Fr√É¬©d√É¬©ric Auburtin'] | E8: ['Fr√É¬©d√É¬©ric Auburtin', 'Jean-Paul Delfino'] | F8: ['G√É¬©rard Depardieu', 'Sam Neill', 'Tim Roth'] | G8: 2.1 | H8: 2014 Not Rated 1h 50m | I8: 2014 | J8: 4.5 | K8: 2 | L8: 10.39238 | M8: =_xlfn.XLOOKUP(A8,Revenue!A:A,Revenue!C:C) -> 168832
A9: House of the Dead | B9: House of the Dead | C9: 7000000 | D9: ['Uwe Boll'] | E9: ['Mark A. Altman', 'Dan Bates', 'Dave Parker'] | F9: ['Jonathan Cherry', 'Tyron Leitso', 'Clint Howard'] | G9: 2.1 | H9: 2003 R 1h 30m | I9: 2003 | J9: 2.6666667 | K9: 2 | L9: 10.953115 | M9: =_xlfn.XLOOKUP(A9,Revenue!A:A,Revenue!C:C) -> 13860078
A10: The Helix√É¬¢√Ç¬Ä√Ç¬¶Loaded | B10: The Helix... Loaded | C10: 1000000 | D10: ['A. Raven Cruz'] | E10: ['A. Raven Cruz'] | F10: ['Scott Levy', 'Vanilla Ice', 'Geremy Dingle'] | G10: 2.1 | H10: 2005 R 1h 37m | I10: 2005 | J10: 2 | K10: 2 | L10: 10.953004 | M10: =_xlfn.XLOOKUP(A10,Revenue!A:A,Revenue!C:C) -> #N/A
A11: Son of the Mask | B11: Son of the Mask | C11: 100000000 | D11: ['Lawrence Guterman'] | E11: ['Lance Khazei'] | F11: ['Jamie Kennedy', 'Traylor Howard', 'Alan Cumming'] | G11: 2.2 | H11: 2005 PG 1h 34m | I11: 2005 | J11: 3.5 | K11: 2 | L11: 14.53559 | M11: =_xlfn.XLOOKUP(A11,Revenue!A:A,Revenue!C:C) -> 59918422
A12: Who's Your Caddy? | B12: Who's Your Caddy? | C12: 7000000 | D12: ['Don Michael Paul'] | E12: ['Don Michael Paul', 'Bradley Allenstein', 'Robert Henny'] | F12: ['Big Boi', 'Jeffrey Jones', 'Terry Crews'] | G12: 2.2 | H12: 2007 PG-13 1h 33m | I12: 2007 | J12: 3 | K12: 3 | L12: 13.30103 | M12: =_xlfn.XLOOKUP(A12,Revenue!A:A,Revenue!C:C) -> 5694308
A13: Rock the House | B13: De Bellinga's: Huis op stelten | C13: 250000 | D13: ['Armando de Boer'] | E13: ['Martijn Koevoets'] | F13: ['Luan Bellinga', 'Lucilla Bellinga', 'Dani√É¬´l Bellinga'] | G13: 2.2 | H13: 2022 1h 5m | I13: 2022 | J13: 2 | K13: 2 | L13: 9.5317343 | M13: =_xlfn.XLOOKUP(A13,Revenue!A:A,Revenue!C:C) -> 0
... A644: Stung | B644: Stung | C644: 2500000 | D644: ['Benni Diez'] | E644: ['Adam Aresty'] | F644: ['Matt O Leary', 'Jessica Cook', 'Lance Henriksen'] | G644: 5.1 | H644: 2015 Not Rated 1h 27m | I644: 2015 | J644: 5 | K644: 5 | L644: 8.1556761 | M644: =_xlfn.XLOOKUP(A644,Revenue!A:A,Revenue!C:C) -> 0
A645: Captive | B645: Captive | C645: 2000000 | D645: ['Gregg Simon'] | E645: ['Travis Seppala'] | F645: ['Scout Taylor-Compton', 'Brendan Fehr', 'Tasie Lawrence'] | G645: 5.1 | H645: 2023 | I645: 2023 | J645: 5 | K645: 5 | L645: 14.654173 | M645: =_xlfn.XLOOKUP(A645,Revenue!A:A,Revenue!C:C) -> 2791973
A646: This Thing of Ours | B646: This Thing of Ours | C646: 2000000 | D646: ['Danny Provenzano'] | E646: ['Ted A. Bohus', 'Danny Provenzano'] | F646: ['Frank Vincent', 'Vincent Pastore', 'Louis Vanaria'] | G646: 5.1 | H646: 2002 Not Rated 1h 40m | I646: 2002 | J646: 5 | K646: 5 | L646: 6.8454435 | M646: =_xlfn.XLOOKUP(A646,Revenue!A:A,Revenue!C:C) -> 37227
A647: Lesbian Vampire Killers | B647: Vampire Killers | C647: 2000000 | D647: ['Phil Claydon'] | E647: ['Stewart Williams', 'Paul Hupfield'] | F647: ['Paul McGann', 'James Corden', 'MyAnna Buring'] | G647: 5.1 | H647: 2009 R 1h 26m | I647: 2009 | J647: 5 | K647: 5 | L647: 13.262839 | M647: =_xlfn.XLOOKUP(A647,Revenue!A:A,Revenue!C:C) -> 3620902
A648: Living Dark: The Story of Ted the Caver | B648: Living Dark: The Story of Ted the Caver | C648: 1750000 | D648: ['David L. Hunt'] | E648: ['David L. Hunt', 'Kevin Brown'] | F648: ['Chris Cleveland', 'Matthew Alan', 'Mark Hayter'] | G648: 5.1 | H648: 2013 PG-13 1h 52m | I648: 2013 | J648: 6 | K648: 5.5 | L648: 3.1705551 | M648: =_xlfn.XLOOKUP(A648,Revenue!A:A,Revenue!C:C) -> 0
A649: Kiljuset! | B649: Kiljuset! | C649: 1606057 | D649: ['Reetta Huhtanen'] | E649: ['Jenny Dahlstr√É¬∂m', 'Jalmari Finne', 'John Lundsten'] | F649: ['Jaakko Hutchings', 'Hugo Koivulehto', 'Nino Kr√É¬∂ger'] | G649: 5.1 | H649: 2022 1h 23m | I649: 2022 | J649: 5 | K649: 5 | L649: 1.9777236 | M649: =_xlfn.XLOOKUP(A649,Revenue!A:A,Revenue!C:C) -> 1029483
A650: I Love Your Work | B650: I Love Your Work | C650: 1600000 | D650: ['Adam Goldberg'] | E650: ['Adrian Butchart', 'Adam Goldberg'] | F650: ['Marisa Coughlan', 'Judy Greer', 'Shalom Harlow'] | G650: 5.1 | H650: 2003 R 1h 51m | I650: 2003 | J650: 5 | K650: 5.25 | L650: 6.1875563 | M650: =_xlfn.XLOOKUP(A650,Revenue!A:A,Revenue!C:C) -> 3264
A651: 31 | B651: 31 | C651: 1500000 | D651: ['Rob Zombie'] | E651: ['Rob Zombie'] | F651: ['Malcolm McDowell', 'Richard Brake', 'Jeff Daniel Phillips'] | G651: 5.1 | H651: 2016 1h 42m | I651: 2016 | J651: 5.6666667 | K651: 6.3333333 | L651: 14.275778 | M651: =_xlfn.XLOOKUP(A651,Revenue!A:A,Revenue!C:C) -> 922727
A652: Forget Me Not | B652: Forget Me Not | C652: 1300000 | D652: ['Tyler Oliver'] | E652: ['Jamieson Stern', 'Tyler Oliver'] | F652: ['Carly Schroeder', 'Cody Linley', 'Brie Gabrielle'] | G652: 5.1 | H652: 2009 R 1h 43m | I652: 2009 | J652: 5 | K652: 5 | L652: 0 | M652: =_xlfn.XLOOKUP(A652,Revenue!A:A,Revenue!C:C) -> 13465
A653: The Sleepwalker (2014) | B653: The Sleepwalker | C653: 1100000 | D653: ['Mona Fastvold'] | E653: ['Brady Corbet', 'Mona Fastvold'] | F653: ['Gitte Witt', 'Christopher Abbott', 'Stephanie Ellis'] | G653: 5.1 | H653: 2014 Not Rated 1h 31m | I653: 2014 | J653: 5 | K653: 5 | L653: 10.185242 | M653: =_xlfn.XLOOKUP(A653,Revenue!A:A,Revenue!C:C) -> 53240
A654: Escape from Tomorrow | B654: Escape from Tomorrow | C654: 650000 | D654: ['Randy Moore'] | E654: ['Randy Moore'] | F654: ['Roy Abramsohn', 'Elena Schuber', 'Katelynn Rodriguez'] | G654: 5.1 | H654: 2013 Not Rated 1h 30m | I654: 2013 | J654: 5 | K654: 5 | L654: 3.6844863 | M654: =_xlfn.XLOOKUP(A654,Revenue!A:A,Revenue!C:C) -> 171962
A655: Civil Brand | B655: Civil Brand | C655: 500000 | D655: ['Neema Barnette'] | E655: ['Preston A. Whitmore II', 'Joyce Renee Lewis'] | F655: ['LisaRaye McCoy', 'N'Bushe Wright', 'Yasiin Bey'] | G655: 5.1 | H655: 2002 R 1h 35m | I655: 2002 | J655: 5 | K655: 5.1666667 | L655: 13.517671 | M655: =_xlfn.XLOOKUP(A655,Revenue!A:A,Revenue!C:C) -> 254293
A656: Love in the Time of Monsters | B656: Love in the Time of Monsters | C656: 500000 | D656: ['Matt Jackson'] | E656: ['Michael Skvarla'] | F656: ['Gena Shaw', 'Kane Hodder', 'Marissa Skell'] | G656: 5.1 | H656: 2014 Not Rated 1h 37m | I656: 2014 | J656: 5 | K656: 5 | L656: 4.603415 | M656: =_xlfn.XLOOKUP(A656,Revenue!A:A,Revenue!C:C) -> 0
A657: Yesterday Was a Lie | B657: Yesterday Was a Lie | C657: 200000 | D657: ['James Kerwin'] | E657: ['James Kerwin'] | F657: ['Kipleigh Brown', 'Chase Masterson', 'John Newton'] | G657: 5.1 | H657: 2009 PG 1h 29m | I657: 2009 | J657: 5 | K657: 5 | L657: 9.973994 | M657: =_xlfn.XLOOKUP(A657,Revenue!A:A,Revenue!C:C) -> 0
A658: Yesterday Was a Lie | B658: Yesterday Was a Lie | C658: 200000 | D658: ['James Kerwin'] | E658: ['James Kerwin'] | F658: ['Kipleigh Brown', 'Chase Masterson', 'John Newton'] | G658: 5.1 | H658: 2009 PG 1h 29m | I658: 2009 | J658: 5 | K658: 5 | L658: 9.973994 | M658: =_xlfn.XLOOKUP(A658,Revenue!A:A,Revenue!C:C) -> 0
A659: The Mummy: Tomb of the Dragon Emperor | B659: The Mummy: Tomb of the Dragon Emperor | C659: 175000000 | D659: ['Rob Cohen'] | E659: ['Alfred Gough', 'Miles Millar', 'John L. Balderston'] | F659: ['Brendan Fraser', 'Jet Li', 'Maria Bello'] | G659: 5.2 | H659: 2008 PG-13 1h 52m | I659: 2008 | J659: 5.6666667 | K659: 6.2222222 | L659: 10.638459 | M659: =_xlfn.XLOOKUP(A659,Revenue!A:A,Revenue!C:C) -> 405760225
A660: Independence Day: Resurgence | B660: Independence Day: Resurgence | C660: 165000000 | D660: ['Roland Emmerich'] | E660: ['Nicolas Wright', 'James A. Woods', 'Dean Devlin'] | F660: ['Liam Hemsworth', 'Jeff Goldblum', 'Bill Pullman'] | G660: 5.2 | H660: 2016 PG-13 2h | I660: 2016 | J660: 7 | K660: 5.4444444 | L660: 13.591065 | M660: =_xlfn.XLOOKUP(A660,Revenue!A:A,Revenue!C:C) -> 384169424
A661: Ast√É¬É√Ç¬©rix aux Jeux Olympiques | B661: Asterix at the Olympic Games | C661: 113500000 | D661: ['Fr√É¬©d√É¬©ric Forestier', 'Thomas Langmann'] | E661: ['Ren√É¬© Goscinny', 'Albert Uderzo', 'Thomas Langmann'] | F661: ['G√É¬©rard Depardieu', 'Clovis Cornillac', 'Beno√É¬Æt Poelvoorde'] | G661: 5.2 | H661: 2008 Not Rated 1h 56m | I661: 2008 | J661: 5 | K661: 5 | L661: 3.6022771 | M661: =_xlfn.XLOOKUP(A661,Revenue!A:A,Revenue!C:C) -> #N/A
A662: A Good Day to Die Hard | B662: A Good Day to Die Hard | C662: 92000000 | D662: ['John Moore'] | E662: ['Skip Woods', 'Roderick Thorp'] | F662: ['Bruce Willis', 'Jai Courtney', 'Sebastian Koch'] | G662: 5.2 | H662: 2013 R 1h 38m | I662: 2013 | J662: 5.6666667 | K662: 6.6666667 | L662: 15.247936 | M662: =_xlfn.XLOOKUP(A662,Revenue!A:A,Revenue!C:C) -> 304249198
A663: xXx: Return of Xander Cage | B663: xXx: Return of Xander Cage | C663: 85000000 | D663: ['D.J. Caruso'] | E663: ['Rich Wilkes', 'F. Scott Frazier'] | F663: ['Vin Diesel', 'Donnie Yen', 'Deepika Padukone'] | G663: 5.2 | H663: 2017 PG-13 1h 47m | I663: 2017 | J663: 6.3333333 | K663: 4.8333333 | L663: 22.338954 | M663: =_xlfn.XLOOKUP(A663,Revenue!A:A,Revenue!C:C) -> 345033359
... A887: The Rhythm Section | B887: The Rhythm Section | C887: 50000000 | D887: ['Reed Morano'] | E887: ['Mark Burnell'] | F887: ['Blake Lively', 'Richard Brake', 'Elly Curtis'] | G887: 5.4 | H887: 2020 R 1h 49m | I887: 2020 | J887: 5 | K887: 5 | L887: 15.977525 | M887: =_xlfn.XLOOKUP(A887,Revenue!A:A,Revenue!C:C) -> 5983043
A888: 65 | B888: 65 | C888: 45000000 | D888: ['Scott Beck', 'Bryan Woods'] | E888: ['Scott Beck', 'Bryan Woods'] | F888: ['Adam Driver', 'Ariana Greenblatt', 'Chloe Coleman'] | G888: 5.4 | H888: 2023 PG-13 1h 33m | I888: 2023 | J888: 5 | K888: 6.6666667 | L888: 15.754391 | M888: =_xlfn.XLOOKUP(A888,Revenue!A:A,Revenue!C:C) -> 56241027
A889: Aliens in the Attic | B889: Aliens in the Attic | C889: 45000000 | D889: ['John Schultz'] | E889: ['Mark Burton', 'Adam F. Goldberg'] | F889: ['Ashley Tisdale', 'Robert Hoffman', 'Carter Jenkins'] | G889: 5.4 | H889: 2009 PG 1h 26m | I889: 2009 | J889: 5 | K889: 5.5 | L889: 17.52385 | M889: =_xlfn.XLOOKUP(A889,Revenue!A:A,Revenue!C:C) -> 59551283
A890: The Glimmer Man | B890: The Glimmer Man | C890: 45000000 | D890: ['John Gray'] | E890: ['Kevin Brodbin'] | F890: ['Steven Seagal', 'Keenen Ivory Wayans', 'Bob Gunton'] | G890: 5.4 | H890: 1996 R 1h 31m | I890: 1996 | J890: 5 | K890: 6 | L890: 9.3291128 | M890: =_xlfn.XLOOKUP(A890,Revenue!A:A,Revenue!C:C) -> 36404841
A891: Red Riding Hood | B891: Red Riding Hood | C891: 42000000 | D891: ['Catherine Hardwicke'] | E891: ['David Leslie Johnson-McGoldrick'] | F891: ['Amanda Seyfried', 'Lukas Haas', 'Gary Oldman'] | G891: 5.4 | H891: 2011 PG-13 1h 40m | I891: 2011 | J891: 6.3333333 | K891: 6.3333333 | L891: 11.033424 | M891: =_xlfn.XLOOKUP(A891,Revenue!A:A,Revenue!C:C) -> 91678442
A892: Get Rich or Die Tryin' | B892: Get Rich or Die Tryin' | C892: 40000000 | D892: ['Jim Sheridan'] | E892: ['Terence Winter'] | F892: ['50 Cent', 'Joy Bryant', 'Adewale Akinnuoye-Agbaje'] | G892: 5.4 | H892: 2005 R 1h 57m | I892: 2005 | J892: 6.3333333 | K892: 8 | L892: 15.495834 | M892: =_xlfn.XLOOKUP(A892,Revenue!A:A,Revenue!C:C) -> 46666955
A893: Season of the Witch | B893: Season of the Witch | C893: 40000000 | D893: ['Dominic Sena'] | E893: ['Bragi F. Schut'] | F893: ['Nicolas Cage', 'Ron Perlman', 'Claire Foy'] | G893: 5.4 | H893: 2011 PG-13 1h 35m | I893: 2011 | J893: 5.3333333 | K893: 5.5 | L893: 15.738688 | M893: =_xlfn.XLOOKUP(A893,Revenue!A:A,Revenue!C:C) -> 91126600
A894: Aloha | B894: Aloha | C894: 37000000 | D894: ['Cameron Crowe'] | E894: ['Cameron Crowe'] | F894: ['Bradley Cooper', 'Rachel McAdams', 'Emma Stone'] | G894: 5.4 | H894: 2015 PG-13 1h 45m | I894: 2015 | J894: 7 | K894: 7 | L894: 16.934696 | M894: =_xlfn.XLOOKUP(A894,Revenue!A:A,Revenue!C:C) -> 25387091
A895: House of Wax | B895: House of Wax | C895: 35000000 | D895: ['Jaume Collet-Serra'] | E895: ['Charles Belden', 'Chad Hayes', 'Carey W. Hayes'] | F895: ['Chad Michael Murray', 'Paris Hilton', 'Elisha Cuthbert'] | G895: 5.4 | H895: 2005 R 1h 53m | I895: 2005 | J895: 6.3333333 | K895: 6 | L895: 19.54098 | M895: =_xlfn.XLOOKUP(A895,Revenue!A:A,Revenue!C:C) -> 70064800
A896: Unfinished Business | B896: Unfinished Business | C896: 35000000 | D896: ['Ken Scott'] | E896: ['Steve Conrad'] | F896: ['Vince Vaughn', 'Dave Franco', 'Tom Wilkinson'] | G896: 5.4 | H896: 2015 R 1h 31m | I896: 2015 | J896: 5.5 | K896: 7.3333333 | L896: 12.989171 | M896: =_xlfn.XLOOKUP(A896,Revenue!A:A,Revenue!C:C) -> 13214051
A897: The Astronaut's Wife | B897: The Astronaut's Wife | C897: 34000000 | D897: ['Rand Ravich'] | E897: ['Rand Ravich'] | F897: ['Charlize Theron', 'Johnny Depp', 'Joe Morton'] | G897: 5.4 | H897: 1999 R 1h 49m | I897: 1999 | J897: 5 | K897: 5 | L897: 17.23049 | M897: =_xlfn.XLOOKUP(A897,Revenue!A:A,Revenue!C:C) -> 10672566
A898: Down to Earth | B898: Down to Earth | C898: 30000000 | D898: ['Chris Weitz', 'Paul Weitz'] | E898: ['Elaine May', 'Warren Beatty', 'Chris Rock'] | F898: ['Chris Rock', 'Regina King', 'Chazz Palminteri'] | G898: 5.4 | H898: 2001 PG-13 1h 27m | I898: 2001 | J898: 6.8333333 | K898: 5.7777778 | L898: 18.390935 | M898: =_xlfn.XLOOKUP(A898,Revenue!A:A,Revenue!C:C) -> 71172251
A899: What's the Worst That Could Happen? | B899: What's the Worst That Could Happen? | C899: 30000000 | D899: ['Sam Weisman'] | E899: ['Donald E. Westlake', 'Matthew Chapman'] | F899: ['Martin Lawrence', 'Danny DeVito', 'John Leguizamo'] | G899: 5.4 | H899: 2001 PG-13 1h 34m | I899: 2001 | J899: 5 | K899: 5.8333333 | L899: 8.456366 | M899: =_xlfn.XLOOKUP(A899,Revenue!A:A,Revenue!C:C) -> 38462071
A900: Fled | B900: Fled | C900: 30000000 | D900: ['Kevin Hooks'] | E900: ['Preston A. Whitmore II'] | F900: ['Laurence Fishburne', 'Stephen Baldwin', 'Will Patton'] | G900: 5.4 | H900: 1996 R 1h 38m | I900: 1996 | J900: 5 | K900: 5.3333333 | L900: 12.71087 | M900: =_xlfn.XLOOKUP(A900,Revenue!A:A,Revenue!C:C) -> 19892205
... A1209: 5 Days of War | B1209: 5 Days of War | C1209: 12000000 | D1209: ['Renny Harlin'] | E1209: ['Mikko Alanne', 'David Battle'] | F1209: ['Rupert Friend', 'Emmanuelle Chriqui', 'Richard Coyle'] | G1209: 5.6 | H1209: 2011 R 1h 53m | I1209: 2011 | J1209: 6.3333333 | K1209: 5.25 | L1209: 16.05535 | M1209: =_xlfn.XLOOKUP(A1209,Revenue!A:A,Revenue!C:C) -> 87793
A1210: 1612 | B1210: 1612: Khroniki smutnogo vremeni | C1210: 12000000 | D1210: ['Vladimir Khotinenko'] | E1210: ['Arif Aliev'] | F1210: ['Pyotr Kislov', 'Michal Zebrowski', 'Artur Smolyaninov'] | G1210: 5.6 | H1210: 2007 Not Rated 2h 24m | I1210: 2007 | J1210: 5 | K1210: 6 | L1210: 11.065505 | M1210: =_xlfn.XLOOKUP(A1210,Revenue!A:A,Revenue!C:C) -> 5400624
A1211: MacGruber | B1211: MacGruber | C1211: 10000000 | D1211: ['Jorma Taccone'] | E1211: ['Will Forte', 'John Solomon', 'Jorma Taccone'] | F1211: ['Will Forte', 'Kristen Wiig', 'Val Kilmer'] | G1211: 5.6 | H1211: 2010 R 1h 30m | I1211: 2010 | J1211: 5.5 | K1211: 4.9444444 | L1211: 14.338623 | M1211: =_xlfn.XLOOKUP(A1211,Revenue!A:A,Revenue!C:C) -> 8629895
A1212: Deuces Wild | B1212: Deuces Wild | C1212: 10000000 | D1212: ['Scott Kalvert'] | E1212: ['Paul Kimatian', 'Christopher Gambale'] | F1212: ['Stephen Dorff', 'Brad Renfro', 'Fairuza Balk'] | G1212: 5.6 | H1212: 2002 R 1h 36m | I1212: 2002 | J1212: 6 | K1212: 5 | L1212: 6.2587847 | M1212: =_xlfn.XLOOKUP(A1212,Revenue!A:A,Revenue!C:C) -> 6244618
A1213: Io sono l√É¬¢√Ç¬Ä√Ç¬ôamore | B1213: Judge Dredd | C1213: 10000000 | D1213: ['Danny Cannon'] | E1213: ['John Wagner', 'Carlos Ezquerra', 'Michael De Luca'] | F1213: ['Sylvester Stallone', 'Armand Assante', 'Rob Schneider'] | G1213: 5.6 | H1213: 1995 R 1h 36m | I1213: 1995 | J1213: 5.3333333 | K1213: 5.5555556 | L1213: 18.148603 | M1213: =_xlfn.XLOOKUP(A1213,Revenue!A:A,Revenue!C:C) -> #N/A
A1214: Jay and Silent Bob Reboot | B1214: Jay and Silent Bob Reboot | C1214: 10000000 | D1214: ['Kevin Smith'] | E1214: ['Kevin Smith'] | F1214: ['Joey Lauren Adams', 'Ben Affleck', 'Fred Armisen'] | G1214: 5.6 | H1214: 2019 R 1h 45m | I1214: 2019 | J1214: 7 | K1214: 7 | L1214: 14.648214 | M1214: =_xlfn.XLOOKUP(A1214,Revenue!A:A,Revenue!C:C) -> 4730228
A1215: Triple Threat | B1215: Triple Threat | C1215: 10000000 | D1215: ['Jesse V. Johnson'] | E1215: ['Joey O Bryan', 'Fangjin Song', 'Paul Staheli'] | F1215: ['Tony Jaa', 'Tiger Hu Chen', 'Iko Uwais'] | G1215: 5.6 | H1215: 2019 R 1h 36m | I1215: 2019 | J1215: 5 | K1215: 5 | L1215: 4.4913617 | M1215: =_xlfn.XLOOKUP(A1215,Revenue!A:A,Revenue!C:C) -> 385651
A1216: Detention | B1216: Detention | C1216: 10000000 | D1216: ['Joseph Kahn'] | E1216: ['Joseph Kahn', 'Mark Palermo'] | F1216: ['Josh Hutcherson', 'Shanley Caswell', 'Spencer Locke'] | G1216: 5.6 | H1216: 2011 R 1h 33m | I1216: 2011 | J1216: 4.5 | K1216: 5 | L1216: 13.967422 | M1216: =_xlfn.XLOOKUP(A1216,Revenue!A:A,Revenue!C:C) -> 0
A1217: The Ice Pirates | B1217: The Ice Pirates | C1217: 9000000 | D1217: ['Stewart Raffill'] | E1217: ['Stewart Raffill', 'Stanford Sherman'] | F1217: ['Robert Urich', 'Mary Crosby', 'Michael D. Roberts'] | G1217: 5.6 | H1217: 1984 PG 1h 31m | I1217: 1984 | J1217: 4 | K1217: 4.5 | L1217: 5.0740481 | M1217: =_xlfn.XLOOKUP(A1217,Revenue!A:A,Revenue!C:C) -> 13075390
A1218: Breakin' All the Rules | B1218: Breakin' All the Rules | C1218: 9000000 | D1218: ['Daniel Taplitz'] | E1218: ['Daniel Taplitz'] | F1218: ['Jamie Foxx', 'Gabrielle Union', 'Morris Chestnut'] | G1218: 5.6 | H1218: 2004 PG-13 1h 25m | I1218: 2004 | J1218: 5 | K1218: 6 | L1218: 7.2304489 | M1218: =_xlfn.XLOOKUP(A1218,Revenue!A:A,Revenue!C:C) -> 12512317
A1219: Skin Trade | B1219: Skin Trade | C1219: 9000000 | D1219: ['Ekachai Uekrongtham'] | E1219: ['Dolph Lundgren', 'Steven Elder', 'Gabriel Dowrick'] | F1219: ['Dolph Lundgren', 'Tony Jaa', 'Ron Perlman'] | G1219: 5.6 | H1219: 2014 R 1h 36m | I1219: 2014 | J1219: 5 | K1219: 5 | L1219: 12.451633 | M1219: =_xlfn.XLOOKUP(A1219,Revenue!A:A,Revenue!C:C) -> 1242
A1220: Club Dread | B1220: Club Dread | C1220: 8500000 | D1220: ['Jay Chandrasekhar'] | E1220: ['Jay Chandrasekhar', 'Kevin Heffernan', 'Steve Lemme'] | F1220: ['Jay Chandrasekhar', 'Bill Paxton', 'Kevin Heffernan'] | G1220: 5.6 | H1220: 2004 R 1h 44m | I1220: 2004 | J1220: 6.3333333 | K1220: 6.3333333 | L1220: 10.800918 | M1220: =_xlfn.XLOOKUP(A1220,Revenue!A:A,Revenue!C:C) -> 7573551
A1221: The Intruder | B1221: The Intruder | C1221: 8000000 | D1221: ['Deon Taylor'] | E1221: ['David Loughery'] | F1221: ['Michael Ealy', 'Meagan Good', 'Dennis Quaid'] | G1221: 5.6 | H1221: 2019 PG-13 1h 42m | I1221: 2019 | J1221: 5.3333333 | K1221: 5.3333333 | L1221: 16.368752 | M1221: =_xlfn.XLOOKUP(A1221,Revenue!A:A,Revenue!C:C) -> 40597401
A1222: A Thin Line Between Love & Hate | B1222: A Thin Line Between Love and Hate | C1222: 8000000 | D1222: ['Martin Lawrence'] | E1222: ['Martin Lawrence', 'Bentley Kyle Evans', 'Kenny Buford'] | F1222: ['Martin Lawrence', 'Lynn Whitfield', 'Regina King'] | G1222: 5.6 | H1222: 1996 R 1h 48m | I1222: 1996 | J1222: 5 | K1222: 5 | L1222: 12.150449 | M1222: =_xlfn.XLOOKUP(A1222,Revenue!A:A,Revenue!C:C) -> 34873513
... A1308: Blue Crush | B1308: Blue Crush | C1308: 30000000 | D1308: ['John Stockwell'] | E1308: ['Susan Orlean', 'Lizzy Weiss', 'John Stockwell'] | F1308: ['Kate Bosworth', 'Michelle Rodriguez', 'Matthew Davis'] | G1308: 5.7 | H1308: 2002 PG-13 1h 44m | I1308: 2002 | J1308: 6 | K1308: 5.5 | L1308: 18.954243 | M1308: =_xlfn.XLOOKUP(A1308,Revenue!A:A,Revenue!C:C) -> 51618420
A1309: Xinhai geming | B1309: 1911 | C1309: 30000000 | D1309: ['Tao Hai', 'Wei Li', 'Guoqiang Tang'] | E1309: ['Xingdong Wang', 'Baoguang Chen'] | F1309: ['Jackie Chan', 'Winston Chao', 'Bingbing Li'] | G1309: 5.7 | H1309: 2011 R 1h 39m | I1309: 2011 | J1309: 5 | K1309: 5 | L1309: 4.5314789 | M1309: =_xlfn.XLOOKUP(A1309,Revenue!A:A,Revenue!C:C) -> 8593154
A1310: Grace of Monaco | B1310: Grace of Monaco | C1310: 30000000 | D1310: ['Olivier Dahan'] | E1310: ['Arash Amel'] | F1310: ['Nicole Kidman', 'Tim Roth', 'Andr√É¬© Penvern'] | G1310: 5.7 | H1310: 2014 Not Rated 1h 43m | I1310: 2014 | J1310: 5 | K1310: 5 | L1310: 11.633468 | M1310: =_xlfn.XLOOKUP(A1310,Revenue!A:A,Revenue!C:C) -> 25199891
A1311: Joyful Noise | B1311: Joyful Noise | C1311: 27500000 | D1311: ['Todd Graff'] | E1311: ['Todd Graff', 'Max Myers'] | F1311: ['Queen Latifah', 'Dolly Parton', 'Keke Palmer'] | G1311: 5.7 | H1311: 2012 PG-13 1h 58m | I1311: 2012 | J1311: 5.6666667 | K1311: 5.25 | L1311: 13.959041 | M1311: =_xlfn.XLOOKUP(A1311,Revenue!A:A,Revenue!C:C) -> 31157914
A1312: Rules Don√É¬¢√Ç¬Ä√Ç¬ôt Apply | B1312: Rules Don't Apply | C1312: 26700000 | D1312: ['Warren Beatty'] | E1312: ['Warren Beatty', 'Bo Goldman'] | F1312: ['Lily Collins', 'Haley Bennett', 'Taissa Farmiga'] | G1312: 5.7 | H1312: 2016 PG-13 2h 7m | I1312: 2016 | J1312: 6.3333333 | K1312: 6.4166667 | L1312: 16.992341 | M1312: =_xlfn.XLOOKUP(A1312,Revenue!A:A,Revenue!C:C) -> #N/A
A1313: Freddy vs. Jason | B1313: Freddy vs. Jason | C1313: 25000000 | D1313: ['Ronny Yu'] | E1313: ['Wes Craven', 'Victor Miller', 'Damian Shannon'] | F1313: ['Robert Englund', 'Ken Kirzinger', 'Kelly Rowland'] | G1313: 5.7 | H1313: 2003 R 1h 37m | I1313: 2003 | J1313: 5.3333333 | K1313: 5.8888889 | L1313: 15.665246 | M1313: =_xlfn.XLOOKUP(A1313,Revenue!A:A,Revenue!C:C) -> 114576403
A1314: Bright Lights, Big City | B1314: Bright Lights, Big City | C1314: 25000000 | D1314: ['James Bridges'] | E1314: ['Jay McInerney'] | F1314: ['Michael J. Fox', 'Kiefer Sutherland', 'Phoebe Cates'] | G1314: 5.7 | H1314: 1988 R 1h 47m | I1314: 1988 | J1314: 5 | K1314: 5 | L1314: 9.3942257 | M1314: =_xlfn.XLOOKUP(A1314,Revenue!A:A,Revenue!C:C) -> 16118077
A1315: Think Like a Man Too | B1315: Think Like a Man Too | C1315: 24000000 | D1315: ['Tim Story'] | E1315: ['Keith Merryman', 'David A. Newman', 'Steve Harvey'] | F1315: ['Kevin Hart', 'Gabrielle Union', 'Wendi McLendon-Covey'] | G1315: 5.7 | H1315: 2014 PG-13 1h 46m | I1315: 2014 | J1315: 6.3333333 | K1315: 5.6666667 | L1315: 13.702206 | M1315: =_xlfn.XLOOKUP(A1315,Revenue!A:A,Revenue!C:C) -> 70027933
A1316: The Marksman | B1316: The Marksman | C1316: 23000000 | D1316: ['Robert Lorenz'] | E1316: ['Chris Charles', 'Danny Kravitz', 'Robert Lorenz'] | F1316: ['Katheryn Winnick', 'Liam Neeson', 'Teresa Ruiz'] | G1316: 5.7 | H1316: 2021 PG-13 1h 48m | I1316: 2021 | J1316: 5.5 | K1316: 5 | L1316: 15.460233 | M1316: =_xlfn.XLOOKUP(A1316,Revenue!A:A,Revenue!C:C) -> 23855847
A1317: Son of God | B1317: Son of God | C1317: 22000000 | D1317: ['Christopher Spencer'] | E1317: ['Richard Bedser', 'Christopher Spencer', 'Colin Swash'] | F1317: ['Diogo Morgado', 'Amber Rose Revah', 'Greg Hicks'] | G1317: 5.7 | H1317: 2014 PG-13 2h 18m | I1317: 2014 | J1317: 5 | K1317: 5 | L1317: 10.514707 | M1317: =_xlfn.XLOOKUP(A1317,Revenue!A:A,Revenue!C:C) -> 70949793
A1318: The Little Vampire | B1318: The Little Vampire | C1318: 22000000 | D1318: ['Uli Edel'] | E1318: ['Angela Sommer-Bodenburg', 'Karey Kirkpatrick', 'Larry Wilson'] | F1318: ['Jonathan Lipnicki', 'Rollo Weeks', 'Richard E. Grant'] | G1318: 5.7 | H1318: 2000 PG 1h 35m | I1318: 2000 | J1318: 6 | K1318: 5.6666667 | L1318: 6.4088325 | M1318: =_xlfn.XLOOKUP(A1318,Revenue!A:A,Revenue!C:C) -> 13560782
A1319: Velvet Buzzsaw | B1319: Velvet Buzzsaw | C1319: 21000000 | D1319: ['Dan Gilroy'] | E1319: ['Dan Gilroy'] | F1319: ['Jake Gyllenhaal', 'Rene Russo', 'Zawe Ashton'] | G1319: 5.7 | H1319: 2019 R 1h 53m | I1319: 2019 | J1319: 6 | K1319: 6.6666667 | L1319: 15.974879 | M1319: =_xlfn.XLOOKUP(A1319,Revenue!A:A,Revenue!C:C) -> 0
A1320: White Chicks | B1320: White Chicks | C1320: 20000000 | D1320: ['Keenen Ivory Wayans'] | E1320: ['Keenen Ivory Wayans', 'Shawn Wayans', 'Marlon Wayans'] | F1320: ['Marlon Wayans', 'Shawn Wayans', 'Busy Philipps'] | G1320: 5.7 | H1320: 2004 PG-13 1h 49m | I1320: 2004 | J1320: 5.3333333 | K1320: 5.4444444 | L1320: 18.674677 | M1320: =_xlfn.XLOOKUP(A1320,Revenue!A:A,Revenue!C:C) -> 111448997
A1321: How Stella Got Her Groove Back | B1321: How Stella Got Her Groove Back | C1321: 20000000 | D1321: ['Kevin Rodney Sullivan'] | E1321: ['Terry McMillan', 'Ron Bass'] | F1321: ['Angela Bassett', 'Taye Diggs', 'Whoopi Goldberg'] | G1321: 5.7 | H1321: 1998 R 2h 4m | I1321: 1998 | J1321: 5 | K1321: 5.8333333 | L1321: 18.90309 | M1321: =_xlfn.XLOOKUP(A1321,Revenue!A:A,Revenue!C:C) -> 37672944
... A1460: Flight of the Intruder | B1460: Flight of the Intruder | C1460: 35000000 | D1460: ['John Milius'] | E1460: ['Stephen Coonts', 'Robert Dillon', 'David Shaber'] | F1460: ['Danny Glover', 'Willem Dafoe', 'Brad Johnson'] | G1460: 5.8 | H1460: 1991 PG-13 1h 55m | I1460: 1991 | J1460: 6 | K1460: 5.1666667 | L1460: 12.491559 | M1460: =_xlfn.XLOOKUP(A1460,Revenue!A:A,Revenue!C:C) -> 14471440
A1461: 1941 | B1461: 1941 | C1461: 32000000 | D1461: ['Steven Spielberg'] | E1461: ['Robert Zemeckis', 'Bob Gale', 'John Milius'] | F1461: ['John Belushi', 'Dan Aykroyd', 'Treat Williams'] | G1461: 5.8 | H1461: 1979 PG 1h 58m | I1461: 1979 | J1461: 8.3333333 | K1461: 7.3333333 | L1461: 7.2503956 | M1461: =_xlfn.XLOOKUP(A1461,Revenue!A:A,Revenue!C:C) -> 94875000
A1462: Laws of Attraction | B1462: Laws of Attraction | C1462: 32000000 | D1462: ['Peter Howitt'] | E1462: ['Aline Brosh McKenna', 'Robert Harling'] | F1462: ['Pierce Brosnan', 'Julianne Moore', 'Parker Posey'] | G1462: 5.8 | H1462: 2004 PG-13 1h 30m | I1462: 2004 | J1462: 6 | K1462: 5.9166667 | L1462: 17.705864 | M1462: =_xlfn.XLOOKUP(A1462,Revenue!A:A,Revenue!C:C) -> 29939591
A1463: Without a Paddle | B1463: Without a Paddle | C1463: 30000000 | D1463: ['Steven Brill'] | E1463: ['Fred Wolf', 'Harris Goldberg', 'Tom Nursall'] | F1463: ['Matthew Lillard', 'Seth Green', 'Dax Shepard'] | G1463: 5.8 | H1463: 2004 PG-13 1h 35m | I1463: 2004 | J1463: 5 | K1463: 5.1111111 | L1463: 12.60206 | M1463: =_xlfn.XLOOKUP(A1463,Revenue!A:A,Revenue!C:C) -> 65121280
A1464: The Prince & Me | B1464: The Prince and Me | C1464: 30000000 | D1464: ['Martha Coolidge'] | E1464: ['Mark Amin', 'Katherine Fugate', 'Jack Amiel'] | F1464: ['Julia Stiles', 'Luke Mably', 'Miranda Richardson'] | G1464: 5.8 | H1464: 2004 PG 1h 51m | I1464: 2004 | J1464: 5 | K1464: 5.2222222 | L1464: 9.7648484 | M1464: =_xlfn.XLOOKUP(A1464,Revenue!A:A,Revenue!C:C) -> 30089110
A1465: Splice | B1465: Splice | C1465: 30000000 | D1465: ['Vincenzo Natali'] | E1465: ['Vincenzo Natali', 'Antoinette Terry Bryant', 'Doug Taylor'] | F1465: ['Adrien Brody', 'Sarah Polley', 'Delphine Chan√É¬©ac'] | G1465: 5.8 | H1465: 2009 R 1h 44m | I1465: 2009 | J1465: 6 | K1465: 5 | L1465: 10.636648 | M1465: =_xlfn.XLOOKUP(A1465,Revenue!A:A,Revenue!C:C) -> 28542494
A1466: 80 for Brady | B1466: 80 for Brady | C1466: 28000000 | D1466: ['Kyle Marvin'] | E1466: ['Sarah Haskins', 'Emily Halpern'] | F1466: ['Lily Tomlin', 'Jane Fonda', 'Rita Moreno'] | G1466: 5.8 | H1466: 2023 PG-13 1h 38m | I1466: 2023 | J1466: 5 | K1466: 6 | L1466: 11.767898 | M1466: =_xlfn.XLOOKUP(A1466,Revenue!A:A,Revenue!C:C) -> 40266090
A1467: Pride and Prejudice and Zombies | B1467: Pride and Prejudice and Zombies | C1467: 28000000 | D1467: ['Burr Steers'] | E1467: ['Burr Steers', 'Jane Austen', 'Seth Grahame-Smith'] | F1467: ['Lily James', 'Sam Riley', 'Jack Huston'] | G1467: 5.8 | H1467: 2016 PG-13 1h 48m | I1467: 2016 | J1467: 6 | K1467: 6.3888889 | L1467: 15.437116 | M1467: =_xlfn.XLOOKUP(A1467,Revenue!A:A,Revenue!C:C) -> 16638300
A1468: Lake Placid | B1468: Lake Placid | C1468: 27000000 | D1468: ['Steve Miner'] | E1468: ['David E. Kelley'] | F1468: ['Bridget Fonda', 'Bill Pullman', 'Oliver Platt'] | G1468: 5.8 | H1468: 1999 R 1h 22m | I1468: 1999 | J1468: 5.6666667 | K1468: 5.5 | L1468: 4.9822712 | M1468: =_xlfn.XLOOKUP(A1468,Revenue!A:A,Revenue!C:C) -> 31770413
A1469: Suspect Zero | B1469: Suspect Zero | C1469: 27000000 | D1469: ['E. Elias Merhige'] | E1469: ['Zak Penn', 'Billy Ray'] | F1469: ['Aaron Eckhart', 'Ben Kingsley', 'Carrie-Anne Moss'] | G1469: 5.8 | H1469: 2004 R 1h 39m | I1469: 2004 | J1469: 5.5 | K1469: 7.1666667 | L1469: 6.7976716 | M1469: =_xlfn.XLOOKUP(A1469,Revenue!A:A,Revenue!C:C) -> 8723600
A1470: Final Destination 3 | B1470: Final Destination 3 | C1470: 25000000 | D1470: ['James Wong'] | E1470: ['Glen Morgan', 'James Wong', 'Jeffrey Reddick'] | F1470: ['Mary Elizabeth Winstead', 'Ryan Merriman', 'Kris Lemche'] | G1470: 5.8 | H1470: 2006 R 1h 33m | I1470: 2006 | J1470: 6 | K1470: 5.5555556 | L1470: 8.5997576 | M1470: =_xlfn.XLOOKUP(A1470,Revenue!A:A,Revenue!C:C) -> 112798051
A1471: What a Girl Wants | B1471: What a Girl Wants | C1471: 25000000 | D1471: ['Dennie Gordon'] | E1471: ['William Douglas-Home', 'Jenny Bicks', 'Elizabeth Chandler'] | F1471: ['Amanda Bynes', 'Colin Firth', 'Kelly Preston'] | G1471: 5.8 | H1471: 2003 PG 1h 45m | I1471: 2003 | J1471: 5.3333333 | K1471: 5.8888889 | L1471: 14.917333 | M1471: =_xlfn.XLOOKUP(A1471,Revenue!A:A,Revenue!C:C) -> 37216643
A1472: Cradle 2 the Grave | B1472: Cradle 2 the Grave | C1472: 25000000 | D1472: ['Andrzej Bartkowiak'] | E1472: ['John O Brien', 'Channing Gibson'] | F1472: ['Jet Li', 'DMX', 'Mark Dacascos'] | G1472: 5.8 | H1472: 2003 R 1h 41m | I1472: 2003 | J1472: 5.3333333 | K1472: 5.75 | L1472: 11.868056 | M1472: =_xlfn.XLOOKUP(A1472,Revenue!A:A,Revenue!C:C) -> 56434942
A1473: Masterminds | B1473: Masterminds | C1473: 25000000 | D1473: ['Jared Hess'] | E1473: ['Chris Bowman', 'Hubbel Palmer', 'Emily Spivey'] | F1473: ['Zach Galifianakis', 'Owen Wilson', 'Kristen Wiig'] | G1473: 5.8 | H1473: 2016 PG-13 1h 35m | I1473: 2016 | J1473: 6 | K1473: 5.3333333 | L1473: 8.1287869 | M1473: =_xlfn.XLOOKUP(A1473,Revenue!A:A,Revenue!C:C) -> 30850666
... A1651: Harriet the Spy | B1651: Harriet the Spy | C1651: 13000000 | D1651: ['Bronwen Hughes'] | E1651: ['Louise Fitzhugh', 'Greg Taylor', 'Julie Talen'] | F1651: ['Michelle Trachtenberg', 'Rosie O Donnell', 'Gregory Smith'] | G1651: 5.9 | H1651: 1996 PG 1h 40m | I1651: 1996 | J1651: 5 | K1651: 5.3333333 | L1651: 16.104258 | M1651: =_xlfn.XLOOKUP(A1651,Revenue!A:A,Revenue!C:C) -> 26570048
A1652: 54 | B1652: 54 | C1652: 13000000 | D1652: ['Mark Christopher'] | E1652: ['Mark Christopher'] | F1652: ['Ryan Phillippe', 'Salma Hayek', 'Neve Campbell'] | G1652: 5.9 | H1652: 1998 R 1h 33m | I1652: 1998 | J1652: 5 | K1652: 5 | L1652: 19.165838 | M1652: =_xlfn.XLOOKUP(A1652,Revenue!A:A,Revenue!C:C) -> 16757163
A1653: Robinson Crusoe | B1653: Robinson Crusoe | C1653: 13000000 | D1653: ['Rod Hardy', 'George Miller'] | E1653: ['Daniel Defoe', 'Christopher Lofton', 'Tracy Keenan Wynn'] | F1653: ['Pierce Brosnan', 'William Takaku', 'Polly Walker'] | G1653: 5.9 | H1653: 1997 PG-13 1h 45m | I1653: 1997 | J1653: 6.5 | K1653: 5.3333333 | L1653: 12.886491 | M1653: =_xlfn.XLOOKUP(A1653,Revenue!A:A,Revenue!C:C) -> 42446455
A1654: The Golden Child | B1654: The Golden Child | C1654: 12000000 | D1654: ['Michael Ritchie'] | E1654: ['Dennis Feldman'] | F1654: ['Eddie Murphy', 'J.L. Reate', 'Charles Dance'] | G1654: 5.9 | H1654: 1986 PG-13 1h 34m | I1654: 1986 | J1654: 5.6666667 | K1654: 5 | L1654: 8.1327686 | M1654: =_xlfn.XLOOKUP(A1654,Revenue!A:A,Revenue!C:C) -> 79817937
A1655: Quarantine | B1655: Quarantine | C1655: 12000000 | D1655: ['John Erick Dowdle'] | E1655: ['John Erick Dowdle', 'Drew Dowdle', 'Jaume Balaguer√É¬≥'] | F1655: ['Jennifer Carpenter', 'Steve Harris', 'Columbus Short'] | G1655: 5.9 | H1655: 2008 R 1h 29m | I1655: 2008 | J1655: 6.6666667 | K1655: 5.7777778 | L1655: 10.844943 | M1655: =_xlfn.XLOOKUP(A1655,Revenue!A:A,Revenue!C:C) -> 41924774
A1656: Katy Perry: Part of Me | B1656: Part of Me | C1656: 12000000 | D1656: ['Dan Cutforth', 'Jane Lipsitz'] | E1656: ['Katy Perry', 'Adam Marcello', 'Casey Hooper'] | F1656: ['Katy Perry', 'Adam Marcello', 'Casey Hooper'] | G1656: 5.9 | H1656: 2012 PG 1h 33m | I1656: 2012 | J1656: 5 | K1656: 5 | L1656: 16.55347 | M1656: =_xlfn.XLOOKUP(A1656,Revenue!A:A,Revenue!C:C) -> 32700439
A1657: Just Wright | B1657: Just Wright | C1657: 12000000 | D1657: ['Sanaa Hamri'] | E1657: ['Michael Elliot'] | F1657: ['Queen Latifah', 'Common', 'Paula Patton'] | G1657: 5.9 | H1657: 2010 PG 1h 40m | I1657: 2010 | J1657: 5.5 | K1657: 5.3333333 | L1657: 13.447158 | M1657: =_xlfn.XLOOKUP(A1657,Revenue!A:A,Revenue!C:C) -> 21867665
A1658: Fortress | B1658: Fortress | C1658: 12000000 | D1658: ['Stuart Gordon'] | E1658: ['Troy Neighbors', 'Steven Feinberg', 'David Venable'] | F1658: ['Christopher Lambert', 'Loryn Locklin', 'Kurtwood Smith'] | G1658: 5.9 | H1658: 1992 R 1h 35m | I1658: 1992 | J1658: 5 | K1658: 5 | L1658: 10.948804 | M1658: =_xlfn.XLOOKUP(A1658,Revenue!A:A,Revenue!C:C) -> 46730578
A1659: Critical Care | B1659: Critical Care | C1659: 12000000 | D1659: ['Sidney Lumet'] | E1659: ['Richard Dooling', 'Steven Schwartz'] | F1659: ['James Spader', 'Kyra Sedgwick', 'Helen Mirren'] | G1659: 5.9 | H1659: 1997 R 1h 47m | I1659: 1997 | J1659: 8.3333333 | K1659: 5 | L1659: 10.851258 | M1659: =_xlfn.XLOOKUP(A1659,Revenue!A:A,Revenue!C:C) -> 220175
A1660: San cheng ji | B1660: A Tale of Three Cities | C1660: 12000000 | D1660: ['Mabel Cheung'] | E1660: ['Mabel Cheung', 'Alex Law'] | F1660: ['Ching Wan Lau', 'Tang Wei', 'Hailu Qin'] | G1660: 5.9 | H1660: 2015 2h 10m | I1660: 2015 | J1660: 5 | K1660: 5 | L1660: 5.2278867 | M1660: =_xlfn.XLOOKUP(A1660,Revenue!A:A,Revenue!C:C) -> 1950194
A1661: Dirty Grandpa | B1661: Dirty Grandpa | C1661: 11500000 | D1661: ['Dan Mazer'] | E1661: ['John Phillips'] | F1661: ['Robert De Niro', 'Zac Efron', 'Zoey Deutch'] | G1661: 5.9 | H1661: 2016 R 1h 42m | I1661: 2016 | J1661: 5 | K1661: 5 | L1661: 18.952647 | M1661: =_xlfn.XLOOKUP(A1661,Revenue!A:A,Revenue!C:C) -> 105078449
...

Sheet Revenue
A1: Movie Name | B1: Budget | C1: Revenue
A2: Avatar: The Way of Water | B2: 460000000 | C2: 2319591720
A3: Avengers: Endgame | B3: 400000000 | C3: 2788912285
A4: Pirates of the Caribbean: On Stranger Tides | B4: 379000000 | C4: 1045713802
A5: Avengers: Age of Ultron | B5: 365000000 | C5: 1395316979
A6: Fast X | B6: 340000000 | C6: 714414576
A7: Star Wars Ep. VII: The Force Awakens | B7: 306000000 | C7: 2064615817
A8: Avengers: Infinity War | B8: 300000000 | C8: 2048359754
A9: Pirates of the Caribbean: At World‚Äôs End | B9: 300000000 | C9: 960996492
A10: Justice League | B10: 300000000 | C10: 655945209
A11: Indiana Jones and the Dial of Destiny | B11: 300000000 | C11: 381561976
A12: Mission: Impossible Dead Reckoning Part One | B12: 290000000 | C12: 566325939
A13: Star Wars: The Rise of Skywalker | B13: 275000000 | C13: 1072767997
... A82: Black Adam | B82: 200000000 | C82: 390323855
A83: 2012 | B83: 200000000 | C83: 757677748
A84: Eternals | B84: 200000000 | C84: 401731759
A85: Fantastic Beasts: The Crimes of Grindelwald | B85: 200000000 | C85: 648455339
A86: Elemental | B86: 200000000 | C86: 486735727
A87: Terminator Salvation | B87: 200000000 | C87: 365491792
A88: Lightyear | B88: 200000000 | C88: 218768299
A89: Jungle Cruise | B89: 200000000 | C89: 210469803
A90: Green Lantern | B90: 200000000 | C90: 219535492
A91: The Flash | B91: 200000000 | C91: 266516138
A92: Fantastic Beasts: The Secrets of Dumbledore | B92: 200000000 | C92: 404560145
A93: Prince of Persia: Sands of Time | B93: 200000000 | C93: 336359676
A94: Killers of the Flower Moon | B94: 200000000 | C94: 154486520
A95: Dark Phoenix | B95: 200000000 | C95: 246356895
... A449: Django Unchained | B449: 100000000 | C449: 449841566
A450: 1917 | B450: 100000000 | C450: 389140440
A451: Little Fockers | B451: 100000000 | C451: 310650574
A452: True Lies | B452: 100000000 | C452: 365300000
A453: American Gangster | B453: 100000000 | C453: 267985456
A454: The Hunger Games: The Ballad of Songbirds & Snakes | B454: 100000000 | C454: 251950041
A455: Cloudy with a Chance of Meatballs | B455: 100000000 | C455: 236827677
A456: The Other Guys | B456: 100000000 | C456: 170936470
A457: Lemony Snicket's A Series of Unfortunate Events | B457: 100000000 | C457: 212956024
A458: The Wolf of Wall Street | B458: 100000000 | C458: 389816136
A459: Epic | B459: 100000000 | C459: 262794441
A460: Eraser | B460: 100000000 | C460: 234400000
A461: The Hunchback of Notre Dame | B461: 100000000 | C461: 325500000
A462: The Emperor's New Groove | B462: 100000000 | C462: 169630573
... A987: The Lego Movie | B987: 60000000 | C987: 468084718
A988: 300 | B988: 60000000 | C988: 454161935
A989: Wild Hogs | B989: 60000000 | C989: 253555383
A990: Marley & Me | B990: 60000000 | C990: 247812011
A991: The Green Mile | B991: 60000000 | C991: 290701374
A992: The Truman Show | B992: 60000000 | C992: 264118201
A993: Sully | B993: 60000000 | C993: 238524556
A994: The Bourne Identity | B994: 60000000 | C994: 214357371
A995: Couples Retreat | B995: 60000000 | C995: 172450423
A996: Goldeneye | B996: 60000000 | C996: 356429933
A997: The Italian Job | B997: 60000000 | C997: 176262839
A998: Daddy Day Care | B998: 60000000 | C998: 164285587
A999: The General\'s Daughter | B999: 60000000 | C999: 149705852
A1000: The Prince of Egypt | B1000: 60000000 | C1000: 218613188
... A1468: The Indian in the Cupboard | B1468: 45000000 | C1468: 35627222
A1469: 65 | B1469: 45000000 | C1469: 56241027
A1470: Cellular | B1470: 45000000 | C1470: 61453420
A1471: Doctor Sleep | B1471: 45000000 | C1471: 71720838
A1472: The Ant Bully | B1472: 45000000 | C1472: 49610898
A1473: Johnny English | B1473: 45000000 | C1473: 161735791
A1474: Dune | B1474: 45000000 | C1474: 27503491
A1475: Aliens in the Attic | B1475: 45000000 | C1475: 59551283
A1476: Across the Universe | B1476: 45000000 | C1476: 29367143
A1477: Revolutionary Road | B1477: 45000000 | C1477: 79604820
A1478: Babylon A.D. | B1478: 45000000 | C1478: 70216497
A1479: Richard Jewell | B1479: 45000000 | C1479: 43092210
A1480: Frankenstein | B1480: 45000000 | C1480: 112006296
A1481: The Glimmer Man | B1481: 45000000 | C1481: 36404841
... A1848: Star Trek: The Motion Picture | B1848: 35000000 | C1848: 139000000
A1849: 21 | B1849: 35000000 | C1849: 159846429
A1850: What Happens in Vegas... | B1850: 35000000 | C1850: 218535708
A1851: Cape Fear | B1851: 35000000 | C1851: 182291969
A1852: The English Patient | B1852: 35000000 | C1852: 231710008
A1853: Hotel for Dogs | B1853: 35000000 | C1853: 122357172
A1854: Guess Who | B1854: 35000000 | C1854: 102115888
A1855: This is 40 | B1855: 35000000 | C1855: 90221182
A1856: L.A. Confidential | B1856: 35000000 | C1856: 126204977
A1857: Sky High | B1857: 35000000 | C1857: 83109359
A1858: In & Out | B1858: 35000000 | C1858: 83226569
A1859: A Nightmare on Elm Street | B1859: 35000000 | C1859: 117729618
A1860: The Cell | B1860: 35000000 | C1860: 104102747
A1861: Species | B1861: 35000000 | C1861: 113354449
... A2022: The Number 23 | B2022: 32000000 | C2022: 77593167
A2023: 1941 | B2023: 32000000 | C2023: 94875000
A2024: Dreamer: Inspired by a True Story | B2024: 32000000 | C2024: 39498360
A2025: Bombshell | B2025: 32000000 | C2025: 61404394
A2026: A History of Violence | B2026: 32000000 | C2026: 61477797
A2027: The Incredible Burt Wonderstone | B2027: 32000000 | C2027: 27392609
A2028: The Quick and the Dead | B2028: 32000000 | C2028: 18552460
A2029: Laws of Attraction | B2029: 32000000 | C2029: 29939591
A2030: Bad Times at the El Royale | B2030: 32000000 | C2030: 31178942
A2031: Going the Distance | B2031: 32000000 | C2031: 43603990
A2032: Bringing Out The Dead | B2032: 32000000 | C2032: 16640210
A2033: Repo Men | B2033: 32000000 | C2033: 18195238
A2034: Dragon Wars: D-War | B2034: 32000000 | C2034: 79915361
A2035: Big George Foreman: The Miraculous Story of the‚Ä¶ | B2035: 32000000 | C2035: 5702966
... A2043: La ch'tite famille | B2043: 31400000 | C2043: 55613061
A2044: 42 | B2044: 31000000 | C2044: 97470701
A2045: Flight | B2045: 31000000 | C2045: 160558438
...
